pycolmap/__init__.py
pycolmap/_core.cpython-39-x86_64-linux-gnu.so
pycolmap/py.typed
pycolmap/utils.py
pycolmap/_core/__init__.pyi
pycolmap/_core/cost_functions.pyi
pycolmap/_core/pyceres.pyi
pycolmap/cost_functions/__init__.py
pycolmap_cuda.libs/libGLX-225e03fe.so.0.0.0
pycolmap_cuda.libs/libGLdispatch-a0d0eb9f.so.0.0.0
pycolmap_cuda.libs/libOpenGL-68996860.so.0.0.0
pycolmap_cuda.libs/libgfortran-9f5e54b8.so.5.0.0
pycolmap_cuda.libs/libgomp-14f972ab.so.1.0.0
pycolmap_cuda.libs/libquadmath-e3cefcd4.so.0.0.0
pycolmap_cuda-3.13.0.dev2.dist-info/METADATA
pycolmap_cuda-3.13.0.dev2.dist-info/WHEEL
pycolmap_cuda-3.13.0.dev2.dist-info/RECORD
pycolmap_cuda-3.13.0.dev2.dist-info/licenses/COPYING.txt
