Metadata-Version: 2.2
Name: pycolmap-cuda
Version: 3.13.0.dev2
Summary: COLMAP bindings
Author-Email: =?utf-8?q?Johannes_Sch=C3=B6nberger?= <jsch@demuc.de>, Mihai Dusmanu <mihai.dusmanu@gmail.com>, Paul-Edouard Sarlin <paul.edouard.sarlin@gmail.com>, Shaohui Liu <b1ueber2y@gmail.com>, Philipp Lindenberger <plindenbe@ethz.ch>
License: BSD-3-Clause
Classifier: License :: OSI Approved :: BSD License
Classifier: Programming Language :: Python :: 3 :: Only
Project-URL: Repository, https://github.com/colmap/colmap
Requires-Python: >=3.9
Requires-Dist: numpy
